swap_module/__init__.py
swap_pkg-1.0.1.dist-info/LICENSE.txt
swap_pkg-1.0.1.dist-info/METADATA
swap_pkg-1.0.1.dist-info/WHEEL
swap_pkg-1.0.1.dist-info/top_level.txt
swap_pkg-1.0.1.dist-info/RECORD
