Metadata-Version: 2.1
Name: swap-pkg
Version: 1.0.1
Summary: Basic Calculator
Home-page: UNKNOWN
Author: SwapnilB
Author-email: swapnilbangar1010@gmail.com
License: UNKNOWN
Platform: UNKNOWN
Classifier: Programming Language :: Python :: 3
Classifier: License :: OSI Approved :: MIT License
Classifier: Operating System :: OS Independent
